setup.py
kulsoft_probability/Binomialdistribution.py
kulsoft_probability/Gaussiandistribution.py
kulsoft_probability/Generaldistribution.py
kulsoft_probability/__init__.py
kulsoft_probability.egg-info/PKG-INFO
kulsoft_probability.egg-info/SOURCES.txt
kulsoft_probability.egg-info/dependency_links.txt
kulsoft_probability.egg-info/not-zip-safe
kulsoft_probability.egg-info/top_level.txt