Metadata-Version: 1.0
Name: kulsoft-probability
Version: 0.1
Summary: Gaussian distributions
Home-page: UNKNOWN
Author: Saad kulumba
Author-email: koogle012@gmail.com
License: UNKNOWN
Platform: UNKNOWN
